mcpf_db/db/__init__.py
mcpf_db/db/types.py
mcpf_db-0.1.0.dist-info/LICENSE
mcpf_db-0.1.0.dist-info/METADATA
mcpf_db-0.1.0.dist-info/WHEEL
mcpf_db-0.1.0.dist-info/RECORD
