Metadata-Version: 2.1
Name: mcpf-db
Version: 0.1.0
Summary: Minimalist Configurable Pipelineing Framework -- General Database Functions
License: MIT
Author: Karoly Bosa
Author-email: karoly.bosa@risc-software.at
Requires-Python: >=3.10,<4.0
Classifier: License :: OSI Approved :: MIT License
Classifier: Programming Language :: Python :: 3
Classifier: Programming Language :: Python :: 3.10
Classifier: Programming Language :: Python :: 3.11
Classifier: Programming Language :: Python :: 3.12
Requires-Dist: mcpf-core (>=0.1.0,<0.2.0)
